horno/__init__.py
horno/datos/Colecciones.py
horno/datos/Configuraciones.py
horno/datos/Encoding.py
horno/datos/Encriptacion.py
horno/datos/Fechas.py
horno/datos/Frames.py
horno/datos/Registro.py
horno/datos/TiposDeDatos.py
horno/datos/__init__.py
horno/datos/bd/ConexionBases.py
horno/datos/bd/ConexionBasesExternas.py
horno/datos/bd/__init__.py
horno/datos/bd/dbfonpy.py
horno/ui/UIControles.py
horno/ui/Vistas.py
horno/ui/__init__.py
horno/utiles/CSV.py
horno/utiles/IO.py
horno/utiles/Logger.py
horno/utiles/Memoria.py
horno/utiles/Metricas.py
horno/utiles/Procesos.py
horno/utiles/Singleton.py
horno/utiles/__init__.py
horno/web/Http.py
horno/web/Json.py
horno/web/__init__.py
horno-1.0.2.35.dist-info/METADATA
horno-1.0.2.35.dist-info/RECORD
horno-1.0.2.35.dist-info/WHEEL
horno-1.0.2.35.dist-info/top_level.txt
