Metadata-Version: 2.1
Name: horno
Version: 1.0.2.35
Summary: Lo que el cuerpo necesita
Home-page: https://github.com/pypa/sampleproject
Author: afs
Author-email: author@example.com
License: UNKNOWN
Platform: UNKNOWN
Classifier: Programming Language :: Python :: 3
Classifier: License :: OSI Approved :: MIT License
Classifier: Operating System :: OS Independent
Requires-Dist: python-dateutil
Requires-Dist: bcrypt
Requires-Dist: passlib
Requires-Dist: unidecode
